auto1/__init__.py
auto1/etl.py
auto1/helper/__init__.py
auto1/helper/helper.py
auto1-0.0.1.dist-info/METADATA
auto1-0.0.1.dist-info/WHEEL
auto1-0.0.1.dist-info/top_level.txt
auto1-0.0.1.dist-info/RECORD
