Metadata-Version: 2.1
Name: auto1
Version: 0.0.1
Summary: AUTO1 ETL Pipeline
Home-page: UNKNOWN
Author: Abdul Salam
Author-email: salamsol96@gmail.com
License: UNKNOWN
Platform: UNKNOWN
Requires-Python: >=3.7, <4
